[
  {
    "title": "Introduction to RAG and Knowledge Retrieval",
    "type": "reading"
  },
  {
    "title": "Embeddings and Vector Representations",
    "type": "reading"
  },
  {
    "title": "Vector Databases: Pinecone, Weaviate, and Chroma",
    "type": "reading"
  },
  {
    "title": "Document Chunking Strategies",
    "type": "reading"
  },
  {
    "title": "Semantic Search and Similarity Metrics",
    "type": "reading"
  },
  {
    "title": "Building a Basic RAG Pipeline",
    "type": "reading"
  },
  {
    "title": "Retrieval Evaluation: Precision, Recall, and NDCG",
    "type": "reading"
  },
  {
    "title": "Hybrid Search: BM25 and Dense Retrieval",
    "type": "reading"
  },
  {
    "title": "Multi-Stage Retrieval and Reranking",
    "type": "reading"
  },
  {
    "title": "Core RAG Skills Exercise",
    "type": "hands-on-exercise"
  },
  {
    "title": "Advanced Chunking: Semantic and Hierarchical",
    "type": "reading"
  },
  {
    "title": "Query Expansion and Reformulation Techniques",
    "type": "reading"
  },
  {
    "title": "Hypothetical Document Embeddings (HyDE)",
    "type": "reading"
  },
  {
    "title": "Contextual Compression and Filtering",
    "type": "reading"
  },
  {
    "title": "Multi-Hop and Iterative Retrieval",
    "type": "reading"
  },
  {
    "title": "RAG Evaluation with the RAGAS Framework",
    "type": "reading"
  },
  {
    "title": "Handling Conflicting and Contradictory Documents",
    "type": "reading"
  },
  {
    "title": "Intermediate RAG Checkpoint",
    "type": "hands-on-exercise"
  },
  {
    "title": "GraphRAG: Knowledge Graph Integration",
    "type": "reading"
  },
  {
    "title": "End-to-End Project: Document Q&A System",
    "type": "capstone_project"
  },
  {
    "title": "Streaming RAG Responses",
    "type": "reading"
  },
  {
    "title": "Long-Context RAG with Late Chunking",
    "type": "reading"
  },
  {
    "title": "Domain-Specific RAG Fine-Tuning",
    "type": "reading"
  },
  {
    "title": "Cache-Augmented Generation",
    "type": "reading"
  },
  {
    "title": "Advanced RAG Patterns Exercise",
    "type": "hands-on-exercise"
  },
  {
    "title": "Production RAG Architecture and Scalability",
    "type": "reading"
  },
  {
    "title": "Indexing Large Corpora Efficiently",
    "type": "reading"
  },
  {
    "title": "Self-Corrective RAG (CRAG)",
    "type": "reading"
  },
  {
    "title": "Agentic RAG: Dynamic and Adaptive Retrieval",
    "type": "reading"
  },
  {
    "title": "Advanced Production Exercise",
    "type": "hands-on-exercise"
  },
  {
    "title": "Multimodal RAG: Images, Tables, and PDFs",
    "type": "lesson"
  },
  {
    "title": "Real-Time RAG with Streaming Ingestion",
    "type": "reading"
  },
  {
    "title": "RAG Security and PII Handling",
    "type": "reading"
  },
  {
    "title": "Cost Optimization for RAG Pipelines",
    "type": "reading"
  },
  {
    "title": "Capstone: Enterprise Knowledge Assistant",
    "type": "capstone_project"
  }
]